FillingTimeSeries/FillingMethods.py
FillingTimeSeries/PreprocessingFillingMethods.py
FillingTimeSeries/__init__.py
FillingTimeSeries-1.0.0.dist-info/LICENSE
FillingTimeSeries-1.0.0.dist-info/LICENSE.txt
FillingTimeSeries-1.0.0.dist-info/METADATA
FillingTimeSeries-1.0.0.dist-info/WHEEL
FillingTimeSeries-1.0.0.dist-info/top_level.txt
FillingTimeSeries-1.0.0.dist-info/RECORD
