Metadata-Version: 2.1
Name: FillingTimeSeries
Version: 1.0.0
Summary: Filling Time series: Package to fill missing values in geophysical time series in Python
Home-page: https://github.com/cigefi-ucr/FillingTimeSeries
Author: Rolando Jesus Duarte Mejias, Erick Rivera Fernandez
Author-email: rolando.duartemejias@ucr.ac.cr
License: MIT
Download-URL: https://github.com/cigefi-ucr/FillingTimeSeries/archive/refs/tags/v_1_0_0.tar.gz
Keywords: Time Series,Missing values,Metereology,Geophysics,Metereological
Platform: UNKNOWN
Classifier: Development Status :: 5 - Production/Stable
Classifier: Intended Audience :: Developers
Classifier: Topic :: Software Development :: Build Tools
Classifier: License :: OSI Approved :: MIT License
Classifier: Programming Language :: Python :: 3
Classifier: Programming Language :: Python :: 3.6
Classifier: Programming Language :: Python :: 3.7
Classifier: Programming Language :: Python :: 3.8
Classifier: Programming Language :: Python :: 3.9
License-File: LICENSE
License-File: LICENSE.txt
